{
  "id": 14384115,
  "start": "2026-06-26T18:41:39Z",
  "end": "2026-06-26T18:45:24Z",
  "ground_station": 1861,
  "transmitter": "C3RnLSSuaKzWhHrtJCqUgu",
  "norad_cat_id": 62391,
  "payload": "https://network-satnogs.freetls.fastly.net/media/data_obs/2026/6/26/18/14384115/satnogs_14384115_2026-06-26T18-41-39.ogg",
  "waterfall": "https://s3.eu-central-1.wasabisys.com/satnogs-network/data_obs/2026/6/26/18/14384115/waterfall_14384115_2026-06-26T18-41-39.png",
  "demoddata": [
    {
      "payload_demod": "https://s3.eu-central-1.wasabisys.com/satnogs-network/data_obs/2026/6/26/18/14384115/data_14384115_2026-06-26T18-43-21"
    }
  ],
  "station_name": "LW2DYB",
  "station_lat": -38.28,
  "station_lng": -57.854,
  "station_alt": 10,
  "vetted_status": "good",
  "vetted_user": null,
  "vetted_datetime": null,
  "archived": false,
  "archive_url": null,
  "client_version": "1.8.1",
  "client_metadata": "{\"radio\": {\"name\": \"gr-satnogs\", \"version\": \"v2.3-compat-xxx-v2.3.5.0\", \"parameters\": {\"soapy-rx-device\": \"driver=rtlsdr\", \"samp-rate-rx\": \"2.048e6\", \"rx-freq\": \"436925000\", \"file-path\": \"/tmp/.satnogs/data/receiving_satnogs_14384115_2026-06-26T18-41-39.out\", \"waterfall-file-path\": \"/tmp/.satnogs/data/receiving_waterfall_14384115_2026-06-26T18-41-39.dat\", \"decoded-data-file-path\": \"/tmp/.satnogs/data/data_14384115\", \"doppler-correction-per-sec\": null, \"lo-offset\": null, \"ppm\": \"-4\", \"rigctl-port\": \"4532\", \"gain-mode\": \"Overall\", \"gain\": \"49.6\", \"antenna\": \"RX\", \"dev-args\": null, \"stream-args\": null, \"tune-args\": null, \"other-settings\": null, \"dc-removal\": \"False\", \"bb-freq\": null, \"bw\": null, \"enable-iq-dump\": \"0\", \"iq-file-path\": null, \"udp-dump-host\": null, \"udp-dump-port\": 57356, \"wpm\": null, \"baudrate\": \"9600\", \"framing\": \"ax25\"}}, \"latitude\": -38.28, \"longitude\": -57.854, \"elevation\": 10, \"frequency\": 436925000}",
  "status": "good",
  "waterfall_status": "unknown",
  "waterfall_status_user": null,
  "waterfall_status_datetime": null,
  "rise_azimuth": 220.0,
  "set_azimuth": 111.0,
  "max_altitude": 35.0,
  "transmitter_uuid": "C3RnLSSuaKzWhHrtJCqUgu",
  "transmitter_description": "Mode U - GFSK9k6 - AX.25 G3RUH",
  "transmitter_type": "Transmitter",
  "transmitter_uplink_low": null,
  "transmitter_uplink_high": null,
  "transmitter_uplink_drift": null,
  "transmitter_downlink_low": 436925000,
  "transmitter_downlink_high": null,
  "transmitter_downlink_drift": null,
  "transmitter_mode": "GFSK",
  "transmitter_invert": false,
  "transmitter_baud": 9600.0,
  "transmitter_updated": "2026-04-15T14:58:58.143125Z",
  "transmitter_status": "active",
  "tle0": "0 LASARSAT",
  "tle1": "1 62391U 24247Q   26177.27700145  .00031954  00000-0  62540-3 0  9991",
  "tle2": "2 62391  44.9729 211.1163 0007201  26.2306 333.8948 15.46877465 84724",
  "tle_source": "Space-Track.org",
  "center_frequency": null,
  "observer": "lw2dyb",
  "observation_frequency": 436925000,
  "transmitter_unconfirmed": false,
  "sat_id": "LLUY-1732-6975-8970-4189",
  "_local_waterfall_path": "/home/verdantfoster/strf-main/pipeline/data/waterfall/14384115.png",
  "_local_metadata_path": "/home/verdantfoster/strf-main/pipeline/data/metadata/14384115.json",
  "_local_image_width": 823,
  "_local_image_height": 1603
}